rdl2nd/__init__.py
rdl2nd/__main__.py
rdl2nd/field.py
rdl2nd-0.1.0.dist-info/LICENSE
rdl2nd-0.1.0.dist-info/METADATA
rdl2nd-0.1.0.dist-info/WHEEL
rdl2nd-0.1.0.dist-info/entry_points.txt
rdl2nd-0.1.0.dist-info/top_level.txt
rdl2nd-0.1.0.dist-info/RECORD
