Metadata-Version: 2.1
Name: rdl2nd
Version: 0.1.0
Summary: It generates registers memory map documentation from SystemRDL input files to NaturalDocs output.
Maintainer-email: Tymoteusz Blazejczyk <tymoteusz.blazejczyk@tymonx.com>
License: Apache-2.0
Project-URL: homepage, https://rdl2nd.xlogic.dev
Project-URL: documentation, https://rdl2nd.xlogic.dev
Project-URL: repository, https://gitlab.com/xlogic/tool/rdl2nd
Keywords: SystemRDL,NaturalDocs,documentation,FPGA,ASIC,RTL,HDL
Classifier: Programming Language :: Python :: 3
License-File: LICENSE
